argsloader/__init__.py
argsloader/base/__init__.py
argsloader/base/exception.py
argsloader/base/result.py
argsloader/base/value.py
argsloader/config/__init__.py
argsloader/config/meta.py
argsloader/units/__init__.py
argsloader/units/base.py
argsloader/units/build.py
argsloader/units/common.py
argsloader/units/enum.py
argsloader/units/func.py
argsloader/units/mathop.py
argsloader/units/numeric.py
argsloader/units/operator.py
argsloader/units/resource.py
argsloader/units/status.py
argsloader/units/string.py
argsloader/units/structure.py
argsloader/units/type.py
argsloader/units/utils.py
argsloader/utils/__init__.py
argsloader/utils/formattree.py
argsloader-0.0.1.dist-info/LICENSE
argsloader-0.0.1.dist-info/METADATA
argsloader-0.0.1.dist-info/WHEEL
argsloader-0.0.1.dist-info/top_level.txt
argsloader-0.0.1.dist-info/RECORD
